<?xml version="1.0" encoding="UTF-8"?><simpledc xmlns:xsi="http://www.w3.org/2001/XMLSchema-instance" xmlns:doc="http://www.lyncode.com/xoai" xsi:noNamespaceSchemaLocation="../schemas/dc.xsd"><title>Structure and Categoricity: Determinacy of Reference and Truth-Value in the Philosophy of Mathematics</title><creator>Button, Tim</creator><creator>Walsh, Sean</creator><description>This is the author accepted manuscript. It is currently under an indefinite embargo pending publication by Oxford University Press.</description><description>This article surveys recent literature by Parsons, McGee, Shapiro and others on the significance of categoricity arguments in the philosophy of mathematics. After discussing whether categoricity arguments are sufficient to secure reference to mathematical structures up to isomorphism, we assess what exactly is achieved by recent ‘internal’ renditions of the famous categoricity arguments for arithmetic and set theory.</description><date>2016-03-15T14:46:33Z</date><date>2016-03-15T14:46:33Z</date><date>2016</date><type>Article</type><type>accepted version</type><identifier>https://www.repository.cam.ac.uk/handle/1810/254508</identifier><language>en</language><publisher>Oxford University Press</publisher></simpledc>