<?xml version="1.0" encoding="UTF-8"?><simpledc xmlns:xsi="http://www.w3.org/2001/XMLSchema-instance" xmlns:doc="http://www.lyncode.com/xoai" xsi:noNamespaceSchemaLocation="../schemas/dc.xsd"><title>Review of 'Debates in the Metaphysics of time', ed. by Nathan Oaklander</title><creator>Deng, Natalja</creator><description>This is the author accepted manuscript. The final version is available from Taylor &amp; Francis at http://dx.doi.org/10.1080/02698595.2015.1179045.</description><date>2016-09-21T11:31:39Z</date><date>2016-09-21T11:31:39Z</date><date>2016-07-21</date><type>Article</type><identifier>https://www.repository.cam.ac.uk/handle/1810/260279</identifier><identifier>10.17863/CAM.4510</identifier><language>en</language><publisher>Taylor &amp; Francis</publisher></simpledc>